microsoft_cdktfconstructs/__init__.py
microsoft_cdktfconstructs/py.typed
microsoft_cdktfconstructs/_jsii/__init__.py
microsoft_cdktfconstructs/_jsii/terraform-cdk-constructs@1.7.1.jsii.tgz
microsoft_cdktfconstructs/azure_actiongroup/__init__.py
microsoft_cdktfconstructs/azure_activitylogalert/__init__.py
microsoft_cdktfconstructs/azure_aks/__init__.py
microsoft_cdktfconstructs/azure_diagnosticsettings/__init__.py
microsoft_cdktfconstructs/azure_dnsforwardingruleset/__init__.py
microsoft_cdktfconstructs/azure_dnsresolver/__init__.py
microsoft_cdktfconstructs/azure_dnszone/__init__.py
microsoft_cdktfconstructs/azure_metricalert/__init__.py
microsoft_cdktfconstructs/azure_networkinterface/__init__.py
microsoft_cdktfconstructs/azure_networksecuritygroup/__init__.py
microsoft_cdktfconstructs/azure_policyassignment/__init__.py
microsoft_cdktfconstructs/azure_policydefinition/__init__.py
microsoft_cdktfconstructs/azure_privatednszone/__init__.py
microsoft_cdktfconstructs/azure_publicipaddress/__init__.py
microsoft_cdktfconstructs/azure_resourcegroup/__init__.py
microsoft_cdktfconstructs/azure_roleassignment/__init__.py
microsoft_cdktfconstructs/azure_roledefinition/__init__.py
microsoft_cdktfconstructs/azure_storageaccount/__init__.py
microsoft_cdktfconstructs/azure_subnet/__init__.py
microsoft_cdktfconstructs/azure_virtualmachine/__init__.py
microsoft_cdktfconstructs/azure_virtualnetwork/__init__.py
microsoft_cdktfconstructs/azure_virtualnetworkgateway/__init__.py
microsoft_cdktfconstructs/azure_virtualnetworkgatewayconnection/__init__.py
microsoft_cdktfconstructs/azure_virtualnetworkmanager/__init__.py
microsoft_cdktfconstructs/azure_vmss/__init__.py
microsoft_cdktfconstructs/core_azure/__init__.py
microsoft_cdktfconstructs/testing/__init__.py
microsoft_cdktfconstructs-1.7.1.dist-info/LICENSE
microsoft_cdktfconstructs-1.7.1.dist-info/METADATA
microsoft_cdktfconstructs-1.7.1.dist-info/WHEEL
microsoft_cdktfconstructs-1.7.1.dist-info/top_level.txt
microsoft_cdktfconstructs-1.7.1.dist-info/RECORD
