Metadata-Version: 2.1
Name: microsoft-cdktfconstructs
Version: 1.7.1
Summary: Azure CDK constructs using AZAPI provider for direct Azure REST API access. Version 1.0.0 - Major breaking change migration from AzureRM to AZAPI.
Home-page: https://github.com/azure/terraform-cdk-constructs.git
Author: Microsoft
License: MIT
Project-URL: Source, https://github.com/azure/terraform-cdk-constructs.git
Classifier: Intended Audience :: Developers
Classifier: Operating System :: OS Independent
Classifier: Programming Language :: JavaScript
Classifier: Programming Language :: Python :: 3 :: Only
Classifier: Programming Language :: Python :: 3.9
Classifier: Programming Language :: Python :: 3.10
Classifier: Programming Language :: Python :: 3.11
Classifier: Typing :: Typed
Classifier: Development Status :: 5 - Production/Stable
Classifier: License :: OSI Approved
Requires-Python: ~=3.9
License-File: LICENSE
Requires-Dist: cdktf ==0.20.8
Requires-Dist: constructs <11.0.0,>=10.3.0
Requires-Dist: jsii <2.0.0,>=1.117.0
Requires-Dist: publication >=0.0.3
Requires-Dist: typeguard <4.3.0,>=2.13.3
